WindTools-0.1.0.dist-info/METADATA
WindTools-0.1.0.dist-info/RECORD
WindTools-0.1.0.dist-info/WHEEL
WindTools-0.1.0.dist-info/top_level.txt
windtools/__init__.py
windtools/coordinate.py
windtools/visualization.py
